<!DOCTYPE QGLVIEWER>
<QGLViewer version="2.6.1">
  <State stereo="false">
    <foregroundColor blue="180" green="180" red="180"/>
    <backgroundColor blue="255" green="255" red="255"/>
  </State>
  <Display FPSIsDisplayed="false" cameraIsEdited="false" axisIsDrawn="false" gridIsDrawn="false"/>
  <Geometry width="1098" posY="141" fullScreen="false" posX="382" height="816"/>
  <Camera>
    <Parameters fieldOfView="0.785398" orthoCoef="0.414214" zNearCoefficient="0.005" sceneRadius="8.4012" Type="PERSPECTIVE" zClippingCoefficient="1.73205">
      <SceneCenter z="0" y="-0.27712" x="0"/>
    </Parameters>
    <Stereo physScreenWidth="0.5" focusDistance="20.2823" IODist="0.062"/>
    <ManipulatedCameraFrame>
      <position z="7.88899" y="0.893297" x="-0.567424"/>
      <orientation q3="-0.996947" q2="0.018727" q0="0.0648308" q1="0.0392798"/>
      <ManipulatedParameters rotSens="1" spinSens="0.3" transSens="1" wheelSens="1" zoomSens="1"/>
      <ManipulatedCameraParameters zoomsOnPivotPoint="false" flySpeed="0.084012" rotatesAroundUpVector="false">
        <sceneUpVector z="0" y="1" x="0"/>
      </ManipulatedCameraParameters>
    </ManipulatedCameraFrame>
  </Camera>
</QGLViewer>
